elgamal/__init__.py
elgamal/elgamal.py
elgamal-0.0.5.dist-info/LICENSE
elgamal-0.0.5.dist-info/METADATA
elgamal-0.0.5.dist-info/WHEEL
elgamal-0.0.5.dist-info/top_level.txt
elgamal-0.0.5.dist-info/RECORD
