Metadata-Version: 2.1
Name: elgamal
Version: 0.0.5
Summary: Elgamal cryptography algorithms
Home-page: https://t.me/sidqdev
Author: Sidq
Author-email: dimax258223@gmail.com
License: UNKNOWN
Platform: UNKNOWN
Classifier: Programming Language :: Python :: 3
Classifier: License :: OSI Approved :: MIT License
Classifier: Operating System :: OS Independent
Requires-Python: >=3.6
